bigplanner/__init__.py
bigplanner/bigplanner.py
bigplanner/definitions.py
bigplanner/cli/__init__.py
bigplanner/cli/config.py
bigplanner/cli/inventory.py
bigplanner/cli/main.py
bigplanner/cli/publish.py
bigplanner/cli/script.py
bigplanner/cli/setup.py
bigplanner/cli/task.py
bigplanner/cli/wingdbstub.py
bigplanner/cli/workspace.py
bigplanner/helpers/__init__.py
bigplanner/helpers/faker.py
bigplanner/helpers/general.py
bigplanner/helpers/loaders.py
bigplanner/helpers/models.py
bigplanner/logic/__init__.py
bigplanner/logic/beacons.py
bigplanner/logic/inventory.py
bigplanner/logic/planner.py
bigplanner/mappers/__init__.py
bigplanner/mappers/beacons.py
bigplanner/models/__init__.py
bigplanner/models/base.py
bigplanner/models/beacons.py
bigplanner/models/bigplanner.py
bigplanner/models/config.py
bigplanner/models/enums.py
bigplanner/models/inventory.py
bigplanner/models/planner.py
bigplanner/models/resource.py
bigplanner/models/script.py
bigplanner/models/task.py
bigplanner/ports/__init__.py
bigplanner/ports/beacons.py
bigplanner/ports/preferences.py
bigplanner/storage/__init__.py
bigplanner/storage/surreal.py
bigplanner-0.1.1.dist-info/AUTHORS.rst
bigplanner-0.1.1.dist-info/LICENSE
bigplanner-0.1.1.dist-info/METADATA
bigplanner-0.1.1.dist-info/WHEEL
bigplanner-0.1.1.dist-info/entry_points.txt
bigplanner-0.1.1.dist-info/top_level.txt
bigplanner-0.1.1.dist-info/RECORD
