Metadata-Version: 2.1
Name: bigplanner
Version: 0.1.1
Summary: A Task Planner for big projects
Home-page: https://github.com/asterio/bigplanner
Author: Asterio Gonzalez
Author-email: asterio.gonzalez@gmail.com
License: MIT license
Keywords: bigplanner
Classifier: Development Status :: 2 - Pre-Alpha
Classifier: Intended Audience :: Developers
Classifier: License :: OSI Approved :: MIT License
Classifier: Natural Language :: English
Classifier: Programming Language :: Python :: 3
Classifier: Programming Language :: Python :: 3.9
Classifier: Programming Language :: Python :: 3.10
Classifier: Programming Language :: Python :: 3.11
Requires-Python: >=3.6
License-File: LICENSE
License-File: AUTHORS.rst
Requires-Dist: agptools
Requires-Dist: syncmodels
Requires-Dist: pydantic
Requires-Dist: datamodel-code-generator
Requires-Dist: datamodel-code-generator[http]
Requires-Dist: datamodel-code-generator[graphql]
Requires-Dist: aiohttp
Requires-Dist: aiocache
Requires-Dist: Click
Requires-Dist: glom
Requires-Dist: jmespath
Requires-Dist: fastapi
Requires-Dist: geopy
Requires-Dist: requests
Requires-Dist: rich
Requires-Dist: surrealdb
Requires-Dist: uvicorn
Requires-Dist: uvicorn[watchgodreload]
Requires-Dist: uvloop
Requires-Dist: watchfiles
Requires-Dist: faker
